cir_alerts/__init__.py
tests/__init__.py
cir_alerts-0.0.1.dist-info/METADATA
cir_alerts-0.0.1.dist-info/WHEEL
cir_alerts-0.0.1.dist-info/top_level.txt
cir_alerts-0.0.1.dist-info/RECORD
