Metadata-Version: 2.1
Name: cir-alerts
Version: 0.0.1
Summary: cir-alerts prototype
Home-page: http://packages.python.org/cir-alerts
Author: Paweł Samoraj
Author-email: samoraj.pawel@gmail.com
License: UNKNOWN
Platform: UNKNOWN
Classifier: Development Status :: 3 - Alpha
